hatch_my_plugin/__about__.py
hatch_my_plugin/__init__.py
hatch_my_plugin/hooks.py
hatch_my_plugin/plugin.py
hatch_my_plugin-0.0.6.dist-info/METADATA
hatch_my_plugin-0.0.6.dist-info/WHEEL
hatch_my_plugin-0.0.6.dist-info/entry_points.txt
hatch_my_plugin-0.0.6.dist-info/licenses/LICENSE.txt
hatch_my_plugin-0.0.6.dist-info/RECORD
