Metadata-Version: 2.1
Name: hatch-my-plugin
Version: 0.0.6
Project-URL: Documentation, https://github.com/unknown/hatch-my-plugin#readme
Project-URL: Issues, https://github.com/unknown/hatch-my-plugin/issues
Project-URL: Source, https://github.com/unknown/hatch-my-plugin
Author-email: warise <example@gmail.com>
License-Expression: MIT
License-File: LICENSE.txt
Classifier: Development Status :: 4 - Beta
Classifier: Framework :: Hatch
Classifier: Programming Language :: Python
Classifier: Programming Language :: Python :: 3.7
Classifier: Programming Language :: Python :: 3.8
Classifier: Programming Language :: Python :: 3.9
Classifier: Programming Language :: Python :: 3.10
Classifier: Programming Language :: Python :: 3.11
Classifier: Programming Language :: Python :: Implementation :: CPython
Classifier: Programming Language :: Python :: Implementation :: PyPy
Requires-Python: >=3.7
